pyign/__PyIGN__.py
pyign/__init__.py
pyign/base/__init__.py
pyign/base/_base_class_.py
pyign/base/sensors.py
pyign/base/states.py
pyign/base/valves.py
pyign/core/__init__.py
pyign/core/auto_core.py
pyign/core/bedrock_core.py
pyign/core/ehms_core.py
pyign/core/notification_core.py
pyign/manifest/__init__.py
pyign/manifest/_built_in_.py
pyign/manifest/_engine_config_.py
pyign/tests/__init__.py
pyign/tests/test_bedrock_core.py
pyign/tests/test_notification_core.py
pyign/tests/test_pyign.py
pyign/tests/test_sensors.py
pyign-1.8.5.dist-info/LICENSE
pyign-1.8.5.dist-info/METADATA
pyign-1.8.5.dist-info/WHEEL
pyign-1.8.5.dist-info/top_level.txt
pyign-1.8.5.dist-info/RECORD
