Metadata-Version: 2.1
Name: pyign
Version: 1.8.5
Summary: OSU HALE rocket engine python control package
Home-page: https://github.com/OSU-Hale/PyIGN_Teststand
Author: ['Devon Burson', 'Karsen Burson']
Author-email: bursond@oregonstate.edu
License: MIT
Platform: UNKNOWN
Classifier: License :: OSI Approved :: MIT License
Classifier: Intended Audience :: Science/Research
Classifier: Natural Language :: English
Classifier: Programming Language :: Python :: 3
Requires-Python: >=3.6, <4
License-File: LICENSE
Requires-Dist: markdown
Requires-Dist: numpy
Requires-Dist: argparse
